src/__init__.py
src/main.py
src/packages.py
src/version.py
automatic_actions-7.5.11.dist-info/LICENSE
automatic_actions-7.5.11.dist-info/METADATA
automatic_actions-7.5.11.dist-info/WHEEL
automatic_actions-7.5.11.dist-info/top_level.txt
automatic_actions-7.5.11.dist-info/RECORD
