Metadata-Version: 2.1
Name: automatic-actions
Version: 7.5.11
Summary: Test lib for automatic actions.
Home-page: https://github.com/cxnt/automatic-actions
Classifier: Development Status :: 5 - Production/Stable
Classifier: Intended Audience :: Developers
Classifier: Intended Audience :: Science/Research
Classifier: Natural Language :: English
Classifier: Programming Language :: Python :: 3.7
Classifier: Programming Language :: Python :: 3.8
Classifier: Programming Language :: Python :: 3.9
Classifier: Programming Language :: Python :: 3.10
Classifier: Programming Language :: Python :: 3.11
Classifier: Topic :: Scientific/Engineering :: Artificial Intelligence
Classifier: Topic :: Software Development :: Libraries :: Python Modules
Requires-Python: >=3.7.1
License-File: LICENSE
Requires-Dist: opencv-python
Requires-Dist: numpy<2.0.0,>=1.19
Requires-Dist: PTable<1.0.0,>=0.9.2
Requires-Dist: pillow<10.0.0,>=5.4.1
Requires-Dist: protobuf<=3.20.3,>=3.14.0
Requires-Dist: python-json-logger<3.0.0,>=0.1.11
Requires-Dist: requests<3.0.0,>=2.27.1
Requires-Dist: requests-toolbelt<1.0.0,>=0.9.1
Requires-Dist: Shapely<2.0.0,>=1.7.1
Requires-Dist: bidict<1.0.0,>=0.21.2
Requires-Dist: varname<1.0.0,>=0.8.1
Requires-Dist: python-dotenv<1.0.0,>=0.19.2
Requires-Dist: pynrrd<1.0.0,>=0.4.2
Requires-Dist: SimpleITK<3.0.0.0,>=2.1.1.2
Requires-Dist: pydicom<3.0.0,>=2.3.0
Requires-Dist: stringcase<2.0.0,>=1.2.0
Requires-Dist: python-magic<1.0.0,>=0.4.25
Requires-Dist: trimesh<4.0.0,>=3.11.2
Requires-Dist: scikit-video<2.0.0,>=1.1.11
Requires-Dist: uvicorn[standard]<1.0.0,>=0.18.2
Requires-Dist: fastapi<1.0.0,>=0.79.0
Requires-Dist: websockets<11.0,>=10.3
Requires-Dist: jinja2<4.0.0,>=3.0.3
Requires-Dist: psutil<6.0.0,>=5.9.0
Requires-Dist: jsonpatch<2.0,>=1.32
Requires-Dist: MarkupSafe<3.0.0,>=2.1.1
Requires-Dist: arel<1.0.0,>=0.2.0
Requires-Dist: tqdm<5.0.0,>=4.62.3
Requires-Dist: pandas<=1.5.2,>=1.1.3
Requires-Dist: async-asgi-testclient
Requires-Dist: PyYAML
Requires-Dist: distinctipy
Requires-Dist: beautifulsoup4
Requires-Dist: numerize
Requires-Dist: ffmpeg-python==0.2.0
Requires-Dist: python-multipart==0.0.5
Provides-Extra: apps
Requires-Dist: uvicorn[standard]<1.0.0,>=0.18.2; extra == "apps"
Requires-Dist: fastapi<1.0.0,>=0.79.0; extra == "apps"
Requires-Dist: websockets<11.0,>=10.3; extra == "apps"
Requires-Dist: jinja2<4.0.0,>=3.0.3; extra == "apps"
Requires-Dist: psutil<6.0.0,>=5.9.0; extra == "apps"
Requires-Dist: jsonpatch<2.0,>=1.32; extra == "apps"
Requires-Dist: MarkupSafe<3.0.0,>=2.1.1; extra == "apps"
Requires-Dist: arel<1.0.0,>=0.2.0; extra == "apps"
Requires-Dist: tqdm<5.0.0,>=4.62.3; extra == "apps"
Requires-Dist: pandas<1.4.0,>=1.1.3; extra == "apps"
Provides-Extra: aug
Requires-Dist: imgaug<1.0.0,>=0.4.0; extra == "aug"
Provides-Extra: docs
Requires-Dist: sphinx==4.4.0; extra == "docs"
Requires-Dist: jinja2==3.0.3; extra == "docs"
Requires-Dist: sphinx-immaterial==0.4.0; extra == "docs"
Requires-Dist: sphinx-copybutton==0.4.0; extra == "docs"
Requires-Dist: sphinx-autodoc-typehints==1.15.3; extra == "docs"
Requires-Dist: sphinxcontrib-details-directive==0.1.0; extra == "docs"
Requires-Dist: myst-parser==0.18.0; extra == "docs"
Provides-Extra: extras
Requires-Dist: docker<6.0.0,>=5.0.3; extra == "extras"
Requires-Dist: imagecorruptions<2.0.0,>=1.1.2; extra == "extras"
Requires-Dist: scikit-image<1.0.0,>=0.17.1; extra == "extras"
Requires-Dist: matplotlib<4.0.0,>=3.3.2; extra == "extras"
Requires-Dist: pascal-voc-writer<1.0.0,>=0.1.4; extra == "extras"
Requires-Dist: scipy<2.0.0,>=1.5.2; extra == "extras"
Requires-Dist: sk-video<2.0.0,>=1.1.10; extra == "extras"
Requires-Dist: pandas<1.4.0,>=1.1.3; extra == "extras"
Requires-Dist: ruamel.yaml==0.17.21; extra == "extras"
Provides-Extra: plugins
Requires-Dist: jsonschema<3.0.0,>=2.6.0; extra == "plugins"
Provides-Extra: sdk-nn-plugins
Requires-Dist: flask-restful<1.0.0,>=0.3.7; extra == "sdk-nn-plugins"
Requires-Dist: Werkzeug<3.0.0,>=1.0.1; extra == "sdk-nn-plugins"
Provides-Extra: sdk-no-usages
Requires-Dist: grpcio<2.0.0,>=1.34.1; extra == "sdk-no-usages"
Requires-Dist: plotly<6.0.0,>=4.11.0; extra == "sdk-no-usages"
Requires-Dist: psutil<6.0.0,>=5.4.5; extra == "sdk-no-usages"
